[{
    "id": 1,
    "image": "https://static.thcdn.com/images/large/webp//productimg/1600/1600/11289609-1174892770940184.jpg",
    "title": "SkinCeuticals C E Ferulic (1 fl. oz.)",
    "price": 169,
    "reviews": 4377,
    "rating": {
      "rate": 3.6,
      "count": 71
    },
    "qty": 1
  },
  {
    "id": 2,
    "image": "https://static.thcdn.com/images/large/webp//productimg/1600/1600/11370303-1074944341868735.jpg",
    "title": "EltaMD UV Clear Broad-Spectrum SPF 46",
    "price": 39,
    "reviews": 4336,
    "rating": {
      "rate": 3.7,
      "count": 16
    },
    "qty": 1
  },
  {
    "id": 3,
    "image": "https://static.thcdn.com/images/large/webp//productimg/1600/1600/12596429-3594871019700125.jpg",
    "title": "SkinMedica TNS Advanced+ Serum (1 oz.)",
    "price": 250.75,
    "reviews": 221,
    "rating": {
      "rate": 3.8,
      "count": 27
    },
    "qty": 1
  },
  {
    "id": 4,
    "image": "https://static.thcdn.com/images/large/webp//productimg/1600/1600/11588281-8764882139037003.jpg",
    "title": "Sunday Riley GOOD GENES All-In-One",
    "price": 122,
    "reviews": 654,
    "rating": {
      "rate": 3.9,
      "count": 41
    },
    "qty": 1
  },
  {
    "id": 5,
    "image": "https://static.thcdn.com/images/large/webp//productimg/1600/1600/11174178-1044909106371632.jpg",
    "title": "Paula's Choice SKIN PERFECTING 2",
    "price": 32,
    "reviews": 374,
    "rating": {
      "rate": 4,
      "count": 63
    },
    "qty": 1
  },
  {
    "id": 6,
    "image": "https://static.thcdn.com/images/large/webp//productimg/1600/1600/12915711-2084866563283492.jpg",
    "title": "Oribe Gold Lust Repair  ",
    "price": 157,
    "reviews": 27,
    "rating": {
      "rate": 4.1,
      "count": 55
    },
    "qty": 1
  },
  {
    "id": 7,
    "image": "https://static.thcdn.com/images/large/webp//productimg/1600/1600/11291496-1824871578503201.jpg",
    "title": "iS Clinical Cleansing Complex (6 fl. oz.)-tin",
    "price": 45,
    "reviews": 849,
    "rating": {
      "rate": 4.2,
      "count": 456
    },
    "qty": 1
  },
  {
    "id": 8,
    "image": "https://static.thcdn.com/images/large/webp//productimg/1600/1600/11370312-1044938634157826.jpg",
    "title": "EltaMD UV Clear Broad-Spectrum SPF 46  ",
    "price": 41,
    "reviews": 1132,
    "rating": {
      "rate": 4.6,
      "count": 678
    }
  }]